{
    "1A7V": {
        "pearson": [
            -0.18286007106260968,
            0.5498689534582808
        ],
        "spearman": [
            -0.20110269146412665,
            0.5100184014313398
        ],
        "count": 13
    },
    "1BA3": {
        "pearson": [
            -0.9011635613941439,
            0.098836438605856
        ],
        "spearman": [
            -0.39999999999999997,
            0.6
        ],
        "count": 4
    },
    "1BFM": {
        "pearson": [
            -1.0,
            1.0
        ],
        "spearman": [
            -0.9999999999999999,
            NaN
        ],
        "count": 2
    },
    "1D5G": {
        "pearson": [
            1.0,
            1.0
        ],
        "spearman": [
            0.9999999999999999,
            NaN
        ],
        "count": 2
    },
    "1DIV": {
        "pearson": [
            -0.6110531382743446,
            2.440195917712251e-06
        ],
        "spearman": [
            -0.5696928965245007,
            1.574347880857332e-05
        ],
        "count": 50
    },
    "1EKG": {
        "pearson": [
            -0.9512506838866218,
            0.04874931611337807
        ],
        "spearman": [
            -0.7999999999999999,
            0.20000000000000007
        ],
        "count": 4
    },
    "1FT8": {
        "pearson": [
            -0.6544808175868254,
            0.01521551862805822
        ],
        "spearman": [
            -0.6648351648351648,
            0.013165575845550252
        ],
        "count": 13
    },
    "1FXA": {
        "pearson": [
            -0.7107704218312572,
            0.014216013166360227
        ],
        "spearman": [
            -0.7636363636363637,
            0.006233059747904751
        ],
        "count": 11
    },
    "1G3P": {
        "pearson": [
            -0.505095962265528,
            0.007204715290085059
        ],
        "spearman": [
            -0.2657300434720433,
            0.18035233038690043
        ],
        "count": 27
    },
    "1GUA": {
        "pearson": [
            -0.531608463895644,
            8.473346193519297e-05
        ],
        "spearman": [
            -0.5462244897959183,
            4.9092820620136355e-05
        ],
        "count": 49
    },
    "1H0X": {
        "pearson": [
            1.0,
            1.0
        ],
        "spearman": [
            0.9999999999999999,
            NaN
        ],
        "count": 2
    },
    "1HCQ": {
        "pearson": [
            -1.0,
            1.0
        ],
        "spearman": [
            -0.9999999999999999,
            NaN
        ],
        "count": 2
    },
    "1ITM": {
        "pearson": [
            0.7359961932417385,
            0.4734282190076534
        ],
        "spearman": [
            1.0,
            0.0
        ],
        "count": 3
    },
    "1IV7": {
        "pearson": [
            -0.8759478134610285,
            0.32047390818661153
        ],
        "spearman": [
            -1.0,
            0.0
        ],
        "count": 3
    },
    "1J8I": {
        "pearson": [
            -0.08922042573408939,
            0.8665244713790122
        ],
        "spearman": [
            -0.08827348295047496,
            0.8679336982351336
        ],
        "count": 6
    },
    "1JLV": {
        "pearson": [
            0.6457418254802408,
            0.5530964688394696
        ],
        "spearman": [
            0.5,
            0.6666666666666667
        ],
        "count": 3
    },
    "1L6H": {
        "pearson": [
            -0.8275726933465207,
            0.37944226274648424
        ],
        "spearman": [
            -0.5,
            0.6666666666666667
        ],
        "count": 3
    },
    "1LVM": {
        "pearson": [
            0.16793003386992175,
            0.7871940834845795
        ],
        "spearman": [
            0.5642880936468347,
            0.32172333582430024
        ],
        "count": 5
    },
    "1N18": {
        "pearson": [
            -0.5628804145739154,
            0.43711958542608453
        ],
        "spearman": [
            -0.6000000000000001,
            0.3999999999999999
        ],
        "count": 4
    },
    "1N88": {
        "pearson": [
            0.05739120365214136,
            0.8268172688074593
        ],
        "spearman": [
            0.1006754316201123,
            0.7006398149982397
        ],
        "count": 17
    },
    "1NM1": {
        "pearson": [
            -1.0,
            1.0
        ],
        "spearman": [
            -0.9999999999999999,
            NaN
        ],
        "count": 2
    },
    "1O1U": {
        "pearson": [
            -0.523886080300658,
            0.28606288232569455
        ],
        "spearman": [
            -0.27322953332351235,
            0.6003545904291114
        ],
        "count": 6
    },
    "1O6X": {
        "pearson": [
            0.009536168320468589,
            0.9681715026639013
        ],
        "spearman": [
            -0.06471032682129335,
            0.7863577306711409
        ],
        "count": 20
    },
    "1OSI": {
        "pearson": [
            0.13802518353057452,
            0.8619748164694254
        ],
        "spearman": [
            0.39999999999999997,
            0.6
        ],
        "count": 4
    },
    "1PFL": {
        "pearson": [
            -0.43123066826166534,
            0.4684666447103618
        ],
        "spearman": [
            -0.3,
            0.6238376647810728
        ],
        "count": 5
    },
    "1PRG": {
        "pearson": [
            0.6942193008589677,
            0.08353346986063608
        ],
        "spearman": [
            0.6785714285714287,
            0.0937502539598313
        ],
        "count": 7
    },
    "1R6R": {
        "pearson": [
            0.3526986591956192,
            0.6473013408043808
        ],
        "spearman": [
            0.39999999999999997,
            0.6
        ],
        "count": 4
    },
    "1SPD": {
        "pearson": [
            -1.0,
            1.0
        ],
        "spearman": [
            -0.9999999999999999,
            NaN
        ],
        "count": 2
    },
    "1X0J": {
        "pearson": [
            -0.4589077596396425,
            0.30030745229963807
        ],
        "spearman": [
            -0.6785714285714287,
            0.0937502539598313
        ],
        "count": 7
    },
    "1XWS": {
        "pearson": [
            0.2677662884777646,
            0.7322337115222353
        ],
        "spearman": [
            -0.39999999999999997,
            0.6
        ],
        "count": 4
    },
    "1XXN": {
        "pearson": [
            0.023347261023802884,
            0.9702760448640292
        ],
        "spearman": [
            0.10259783520851543,
            0.8695979205185651
        ],
        "count": 5
    },
    "1XZO": {
        "pearson": [
            -0.12738069268130986,
            0.8726193073186901
        ],
        "spearman": [
            0.0,
            1.0
        ],
        "count": 4
    },
    "2BJD": {
        "pearson": [
            -0.9966624073045801,
            0.05202746364472187
        ],
        "spearman": [
            -1.0,
            0.0
        ],
        "count": 3
    },
    "2C9Q": {
        "pearson": [
            -1.0,
            1.0
        ],
        "spearman": [
            -0.9999999999999999,
            NaN
        ],
        "count": 2
    },
    "2CLR": {
        "pearson": [
            -0.8858966616037779,
            0.11410333839622222
        ],
        "spearman": [
            -1.0,
            0.0
        ],
        "count": 4
    },
    "2DVV": {
        "pearson": [
            -1.0,
            1.0
        ],
        "spearman": [
            -0.9999999999999999,
            NaN
        ],
        "count": 2
    },
    "2HBB": {
        "pearson": [
            -0.6189574139114015,
            4.535021300077153e-06
        ],
        "spearman": [
            -0.6789194536163939,
            2.1461098161916547e-07
        ],
        "count": 46
    },
    "2JIE": {
        "pearson": [
            -0.17512832854855426,
            0.2190017456131182
        ],
        "spearman": [
            -0.13067873303167418,
            0.3607038284597893
        ],
        "count": 51
    },
    "2JUC": {
        "pearson": [
            -0.100053806805326,
            0.9361970120040257
        ],
        "spearman": [
            -0.5,
            0.6666666666666667
        ],
        "count": 3
    },
    "2KJ3": {
        "pearson": [
            -0.35180740164821583,
            0.35316851961734264
        ],
        "spearman": [
            -0.08475793795260131,
            0.8283628971177416
        ],
        "count": 9
    },
    "2KS4": {
        "pearson": [
            1.0,
            1.0
        ],
        "spearman": [
            0.9999999999999999,
            NaN
        ],
        "count": 2
    },
    "2LTB": {
        "pearson": [
            0.2604798974858992,
            0.6181169052491047
        ],
        "spearman": [
            0.2571428571428572,
            0.6227871720116618
        ],
        "count": 6
    },
    "2M5S": {
        "pearson": [
            -1.0,
            1.0
        ],
        "spearman": [
            -0.9999999999999999,
            NaN
        ],
        "count": 2
    },
    "2MPC": {
        "pearson": [
            -0.7703036368232069,
            0.4402092999141375
        ],
        "spearman": [
            -0.5,
            0.6666666666666667
        ],
        "count": 3
    },
    "2NTE": {
        "pearson": [
            -1.0,
            1.0
        ],
        "spearman": [
            -0.9999999999999999,
            NaN
        ],
        "count": 2
    },
    "2PR5": {
        "pearson": [
            -0.44964811995698495,
            0.07016008532048884
        ],
        "spearman": [
            -0.4687120092680836,
            0.05772283073741239
        ],
        "count": 17
    },
    "2PTL": {
        "pearson": [
            0.05927527532340971,
            0.6311159041835462
        ],
        "spearman": [
            0.03718373327610556,
            0.7633807387206113
        ],
        "count": 68
    },
    "2RPN": {
        "pearson": [
            1.0,
            1.0
        ],
        "spearman": [
            0.9999999999999999,
            NaN
        ],
        "count": 2
    },
    "2VY0": {
        "pearson": [
            -1.0,
            1.0
        ],
        "spearman": [
            -0.9999999999999999,
            NaN
        ],
        "count": 2
    },
    "2WQG": {
        "pearson": [
            -0.058873149911695066,
            0.7616162909074263
        ],
        "spearman": [
            -0.07613446506264049,
            0.6946647453690972
        ],
        "count": 29
    },
    "2ZTA": {
        "pearson": [
            -0.08957628092682703,
            0.8329407505936695
        ],
        "spearman": [
            0.07142857142857144,
            0.8665262706759088
        ],
        "count": 8
    },
    "3BCI": {
        "pearson": [
            1.0,
            1.0
        ],
        "spearman": [
            0.9999999999999999,
            NaN
        ],
        "count": 2
    },
    "3C2I": {
        "pearson": [
            0.09280422106549192,
            0.77421702937603
        ],
        "spearman": [
            -0.04895104895104895,
            0.8799185788786749
        ],
        "count": 12
    },
    "3D2A": {
        "pearson": [
            -0.6619177489875707,
            0.5394856028506624
        ],
        "spearman": [
            -0.5,
            0.6666666666666667
        ],
        "count": 3
    },
    "3D3B": {
        "pearson": [
            0.3292132209862657,
            0.5885324871770904
        ],
        "spearman": [
            -0.09999999999999999,
            0.8728885715695383
        ],
        "count": 5
    },
    "3DV0": {
        "pearson": [
            -0.4753175474352219,
            0.00688632823306565
        ],
        "spearman": [
            -0.4811644047941608,
            0.006138395533279337
        ],
        "count": 31
    },
    "3G1G": {
        "pearson": [
            0.772301466135411,
            0.22769853386458916
        ],
        "spearman": [
            0.7999999999999999,
            0.20000000000000007
        ],
        "count": 4
    },
    "3K82": {
        "pearson": [
            0.114604543729738,
            0.9268798192230143
        ],
        "spearman": [
            -0.5,
            0.6666666666666667
        ],
        "count": 3
    },
    "3MON": {
        "pearson": [
            -1.0,
            1.0
        ],
        "spearman": [
            -0.9999999999999999,
            NaN
        ],
        "count": 2
    },
    "3O39": {
        "pearson": [
            -0.643893310936745,
            0.16763866489681736
        ],
        "spearman": [
            -0.7142857142857143,
            0.1107871720116617
        ],
        "count": 6
    },
    "3S4M": {
        "pearson": [
            -0.6511389184555623,
            0.34886108154443773
        ],
        "spearman": [
            -0.39999999999999997,
            0.6
        ],
        "count": 4
    },
    "4BUQ": {
        "pearson": [
            -1.0,
            1.0
        ],
        "spearman": [
            -0.9999999999999999,
            NaN
        ],
        "count": 2
    },
    "4HE7": {
        "pearson": [
            0.1427855898964706,
            0.9087881271578367
        ],
        "spearman": [
            0.5,
            0.6666666666666667
        ],
        "count": 3
    },
    "4N6V": {
        "pearson": [
            -0.2578564678598199,
            0.8339676615573218
        ],
        "spearman": [
            -0.5,
            0.6666666666666667
        ],
        "count": 3
    },
    "4WAA": {
        "pearson": [
            -0.2765247110186945,
            0.8216344710049956
        ],
        "spearman": [
            -0.5,
            0.6666666666666667
        ],
        "count": 3
    },
    "5JXB": {
        "pearson": [
            NaN,
            NaN
        ],
        "spearman": [
            NaN,
            NaN
        ],
        "count": 2
    },
    "5VP3": {
        "pearson": [
            -0.9954493514797077,
            0.06075703872753026
        ],
        "spearman": [
            -1.0,
            0.0
        ],
        "count": 3
    },
    "overall": {
        "pearson": [
            -0.16095129714496537,
            2.8829047674892864e-05
        ],
        "spearman": [
            -0.1842368350843588,
            1.6065259194349147e-06
        ],
        "count": 669
    }
}